geopandas/__init__.py
geopandas/_compat.py
geopandas/_config.py
geopandas/_vectorized.py
geopandas/_version.py
geopandas/array.py
geopandas/base.py
geopandas/conftest.py
geopandas/geodataframe.py
geopandas/geoseries.py
geopandas/plotting.py
geopandas/sindex.py
geopandas/testing.py
geopandas/datasets/__init__.py
geopandas/datasets/naturalearth_creation.py
geopandas/datasets/nybb_16a.zip
geopandas/datasets/naturalearth_cities/naturalearth_cities.README.html
geopandas/datasets/naturalearth_cities/naturalearth_cities.VERSION.txt
geopandas/datasets/naturalearth_cities/naturalearth_cities.cpg
geopandas/datasets/naturalearth_cities/naturalearth_cities.dbf
geopandas/datasets/naturalearth_cities/naturalearth_cities.prj
geopandas/datasets/naturalearth_cities/naturalearth_cities.shp
geopandas/datasets/naturalearth_cities/naturalearth_cities.shx
geopandas/datasets/naturalearth_lowres/naturalearth_lowres.cpg
geopandas/datasets/naturalearth_lowres/naturalearth_lowres.dbf
geopandas/datasets/naturalearth_lowres/naturalearth_lowres.prj
geopandas/datasets/naturalearth_lowres/naturalearth_lowres.shp
geopandas/datasets/naturalearth_lowres/naturalearth_lowres.shx
geopandas/io/__init__.py
geopandas/io/arrow.py
geopandas/io/file.py
geopandas/io/sql.py
geopandas/tests/__init__.py
geopandas/tests/test_api.py
geopandas/tests/test_array.py
geopandas/tests/test_compat.py
geopandas/tests/test_config.py
geopandas/tests/test_crs.py
geopandas/tests/test_datasets.py
geopandas/tests/test_dissolve.py
geopandas/tests/test_extension_array.py
geopandas/tests/test_geocode.py
geopandas/tests/test_geodataframe.py
geopandas/tests/test_geom_methods.py
geopandas/tests/test_geoseries.py
geopandas/tests/test_merge.py
geopandas/tests/test_overlay.py
geopandas/tests/test_pandas_methods.py
geopandas/tests/test_plotting.py
geopandas/tests/test_show_versions.py
geopandas/tests/test_sindex.py
geopandas/tests/test_testing.py
geopandas/tests/test_types.py
geopandas/tests/util.py
geopandas/tools/__init__.py
GeologyUtils-0.0.1.dist-info/LICENSE.txt
GeologyUtils-0.0.1.dist-info/METADATA
GeologyUtils-0.0.1.dist-info/WHEEL
GeologyUtils-0.0.1.dist-info/top_level.txt
GeologyUtils-0.0.1.dist-info/RECORD
